logobin/__init__.py
logobin/__main__.py
logobin-1.0.3.dist-info/LICENSE
logobin-1.0.3.dist-info/METADATA
logobin-1.0.3.dist-info/NOTICE
logobin-1.0.3.dist-info/WHEEL
logobin-1.0.3.dist-info/entry_points.txt
logobin-1.0.3.dist-info/top_level.txt
logobin-1.0.3.dist-info/RECORD
