Metadata-Version: 2.1
Name: logobin
Version: 1.0.3
Summary: Command line utility for creating or unpacking boot logos for 8227l-based Android head units
Home-page: https://github.com/threadreaper/8227logo
Author: Michael Podrybau
Author-email: threadreaper@gmail.com
License: Apache License 2.0
Platform: UNKNOWN
Classifier: Programming Language :: Python :: 3
Classifier: License :: OSI Approved :: Apache Software License
Classifier: Operating System :: OS Independent
Classifier: Environment :: Console
Classifier: Natural Language :: English
Classifier: Intended Audience :: End Users/Desktop
Requires-Python: >=3.6
Requires-Dist: argparse
Requires-Dist: pathlib
